haske/__init__.py
haske/__main__.py
haske/admin.py
haske/app.py
haske/auth.py
haske/cache.py
haske/cli.py
haske/exceptions.py
haske/middleware.py
haske/orm.py
haske/request.py
haske/response.py
haske/routing.py
haske/static.py
haske/templates.py
haske/ws.py
haske-0.2.14.dist-info/licenses/LICENSE
haske-0.2.14.dist-info/METADATA
haske-0.2.14.dist-info/WHEEL
haske-0.2.14.dist-info/top_level.txt
haske-0.2.14.dist-info/RECORD
